supabase_client/__init__.py
supabase_client/_http_client.py
supabase_client/_supabase_clients.py
supabase_client/querybuilders.py
supabase_client/supabase_client.py
supabase_client/supebase_exceptions.py
supabase_client-0.2.4.dist-info/METADATA
supabase_client-0.2.4.dist-info/RECORD
supabase_client-0.2.4.dist-info/WHEEL
supabase_client-0.2.4.dist-info/top_level.txt
