Metadata-Version: 2.1
Name: supabase-client
Version: 0.2.4
Summary: A supabase client for Python
Home-page: https://github.com/keosariel/supabase-client
Author: Kenneth Gabriel
Author-email: kennethgabriel78@gmail.com
License: MIT
Keywords: python,supabase,request,aiohttp,client
Platform: UNKNOWN
Classifier: Development Status :: 1 - Planning
Classifier: Intended Audience :: Developers
Classifier: Programming Language :: Python :: 3
Classifier: Operating System :: Unix
Classifier: Operating System :: MacOS :: MacOS X
Classifier: Operating System :: Microsoft :: Windows
Provides-Extra: dotenv
Requires-Dist: aiohttp (>=3.7.4)
Provides-Extra: dotenv
Requires-Dist: python-dotenv; extra == 'dotenv'
